[
  {
    "title": "创作者联盟集结 - Kaia x LINE NEXT",
    "date": "2024年11月11日 15:00-19:00",
    "location": "曼谷 Double Standard",
    "description": "Web3创作者聚会，介绍Kaia Wave项目",
    "registrationLink": "https://lu.ma/mfa09bp5",
    "hostBy": "Kaia Foundation & LINE NEXT",
    "category": "networking"
  },
  {
    "title": "Kaia黑客屋：城堡攻防CTF挑战赛",
    "date": "2024年9月16-20日 10:00-17:00",
    "location": "新加坡 Kaia Labs",
    "description": "Token2049期间的区块链安全挑战赛",
    "registrationLink": "https://lu.ma/3x6mxsxr",
    "hostBy": "Kaia",
    "category": "hackathon"
  },
  {
    "title": "Shard迪拜峰会2025：AI、加密与资本汇聚",
    "date": "2025年5月3日 13:00-18:00",
    "location": "迪拜 Al Safa艺术设计图书馆",
    "description": "Web3行业领袖峰会，探讨AI与加密货币融合",
    "registrationLink": "https://lu.ma/e7an1q6h",
    "hostBy": "Sharding Capital",
    "category": "summit"
  },
  {
    "title": "Shard x Kaia建设者早餐会",
    "date": "2025年5月2日 09:30-12:00",
    "location": "迪拜 FORMA",
    "description": "行业领袖深度交流与合作探讨",
    "registrationLink": "https://lu.ma/b2nh1jlm",
    "hostBy": "Sharding Capital & Kaia",
    "category": "networking"
  },
  {
    "title": "下一代dApp聚会",
    "date": "2025年4月8日 14:00-18:00",
    "location": "香港 Google办公室",
    "description": "dApp开发者与Google Cloud专家交流",
    "registrationLink": "https://lu.ma/9ik2uk27",
    "hostBy": "ABGA, Kaia & Google Cloud",
    "category": "meetup"
  },
  {
    "title": "香港K-BBQ DAO",
    "date": "2025年4月7日 17:30",
    "location": "香港岛",
    "description": "韩式烤肉主题的Web3社交聚会",
    "registrationLink": "https://lu.ma/1qsfr5mt",
    "hostBy": "Kaia & ABGA",
    "category": "social"
  },
  {
    "title": "Catizen FunFi未来狂欢",
    "date": "2025年4月6日 18:00",
    "location": "待公布",
    "description": "游戏与Web3融合的娱乐金融体验",
    "registrationLink": "https://lu.ma/8wesjc7f",
    "hostBy": "Catizen & Kaia",
    "category": "gaming"
  },
  {
    "title": "Kaia社区连接",
    "date": "2025年2月19日 14:00",
    "location": "香港 BRICK LANE",
    "description": "Kaia区块链社区网络聚会",
    "registrationLink": "https://lu.ma/evtzh63w",
    "hostBy": "ABGA, Kaia & Animoca Brands",
    "category": "community"
  },
  {
    "title": "MKGA香港 - 项目路演日",
    "date": "2025年2月18日 16:00",
    "location": "香港 BRICK LANE Gallery",
    "description": "Kaia项目路演与社交派对",
    "registrationLink": "https://lu.ma/5kvow65x",
    "hostBy": "Kaia Foundation",
    "category": "pitch"
  },
  {
    "title": "影响者见面会：走向未来",
    "date": "2025年2月18日 14:00",
    "location": "香港岛",
    "description": "Web3影响者与项目方对接",
    "registrationLink": "https://lu.ma/gbdvcc37",
    "hostBy": "Kaia & OKX Wallet",
    "category": "networking"
  },
  {
    "title": "乘风破浪Kaia：台北网络夜",
    "date": "2024年12月12日 18:00",
    "location": "台北 The Fox Kitchen & Bar",
    "description": "台北Kaia生态系统网络聚会",
    "registrationLink": "https://lu.ma/mno4feyg",
    "hostBy": "Kaia & LINE NEXT",
    "category": "networking"
  },
  {
    "title": "Kaia网络夜 - Kaia x LINE NEXT",
    "date": "2024年11月12日 18:00-19:00",
    "location": "曼谷 ZillaSpace",
    "description": "Kaia与LINE NEXT合作网络活动",
    "registrationLink": "https://lu.ma/xijguduf",
    "hostBy": "Kaia Foundation & LINE NEXT",
    "category": "networking"
  },
  {
    "title": "乘风破浪Kaia：曼谷版",
    "date": "2024年11月12日 15:00-16:00",
    "location": "曼谷 ZillaSpace",
    "description": "曼谷Web3生态系统展示",
    "registrationLink": "https://lu.ma/hdb1dwvq",
    "hostBy": "Kaia Foundation",
    "category": "showcase"
  },
  {
    "title": "GM早餐会：VC与创始人@Token 2049",
    "date": "2024年9月18日 08:30",
    "location": "新加坡",
    "description": "Token 2049期间的投资人早餐会",
    "registrationLink": "https://lu.ma/rdcccy7s",
    "hostBy": "SNZ Holding & K300 Ventures",
    "category": "breakfast"
  },
  {
    "title": "乘风破浪Kaia - 晚间场",
    "date": "2024年9月17日 17:00",
    "location": "新加坡 红点设计博物馆",
    "description": "Token 2049晚间Kaia生态展示",
    "registrationLink": "https://lu.ma/ex99s2jo",
    "hostBy": "Kaia",
    "category": "showcase"
  },
  {
    "title": "乘风破浪Kaia - 午间场",
    "date": "2024年9月17日 12:00",
    "location": "新加坡 红点设计博物馆",
    "description": "Token 2049午间Kaia展示与交流",
    "registrationLink": "https://lu.ma/ex99s2jo",
    "hostBy": "Kaia",
    "category": "showcase"
  },
  {
    "title": "KSL 2024：网络夜",
    "date": "2024年9月2日 18:00-19:00",
    "location": "首尔 Peaches. D8NE",
    "description": "Kaia Square Lounge会议网络活动",
    "registrationLink": "https://lu.ma/KSL2024Networking",
    "hostBy": "Kaia",
    "category": "networking"
  },
  {
    "title": "Kaia广场休息室2024",
    "date": "2024年9月2日 10:00-11:00",
    "location": "首尔 Peaches. D8NE",
    "description": "Kaia区块链主要会议活动",
    "registrationLink": "https://lu.ma/KSL2024",
    "hostBy": "Kaia",
    "category": "conference"
  }
] 